video_montage/__init__.py
video_montage/utils.py
video_montage/video_grid_montage.py
video_montage/video_sequence_montage.py
video_montage-0.2.1.dist-info/LICENSE
video_montage-0.2.1.dist-info/METADATA
video_montage-0.2.1.dist-info/WHEEL
video_montage-0.2.1.dist-info/entry_points.txt
video_montage-0.2.1.dist-info/top_level.txt
video_montage-0.2.1.dist-info/RECORD
