Metadata-Version: 2.1
Name: video-montage
Version: 0.2.1
Summary: Easily create a video montage (either a sequence or a grid of videos)
Home-page: https://github.com/tylerlum/video_montage
Author: Tyler Lum
Author-email: tylergwlum@gmail.com
Keywords: python,video,montage,grid,sequence
Classifier: Intended Audience :: Developers
Classifier: Operating System :: OS Independent
Classifier: Programming Language :: Python :: 3
License-File: LICENSE
Requires-Dist: moviepy <2
Requires-Dist: typed-argument-parser
Requires-Dist: pillow <10
